LICENSE
setup.py
mhlb/__init__.py
mhlb/mhlb.py
mhlb.egg-info/PKG-INFO
mhlb.egg-info/SOURCES.txt
mhlb.egg-info/dependency_links.txt
mhlb.egg-info/requires.txt
mhlb.egg-info/top_level.txt